django_glide/__init__.py
django_glide/config.py
django_glide/templates/assets.html
django_glide/templates/glide/carousel.html
django_glide/templates/glide/slide.html
django_glide/templates/swiper/carousel.html
django_glide/templates/swiper/slide.html
django_glide/templatetags/__init__.py
django_glide/templatetags/glide_tags.py
django_glide-1.0.0.dist-info/licenses/LICENSE
django_glide-1.0.0.dist-info/METADATA
django_glide-1.0.0.dist-info/WHEEL
django_glide-1.0.0.dist-info/top_level.txt
django_glide-1.0.0.dist-info/RECORD
