Metadata-Version: 2.4
Name: django-glide
Version: 1.0.0
Summary: Glide JS integration for Django
Home-page: https://github.com/KalvadTech/django-glide/
Author: Pierre Guillemot
Author-email: pierre@kalvad.com
License: MIT
Classifier: Framework :: Django
Classifier: Programming Language :: Python :: 3
Requires-Python: >=3
License-File: LICENSE
Requires-Dist: Django>=3
Provides-Extra: dev
Requires-Dist: build==1.3.0; extra == "dev"
Requires-Dist: ruff==0.14.5; extra == "dev"
Requires-Dist: tox==4.32.0; extra == "dev"
Requires-Dist: ty==0.0.1-alpha.19; extra == "dev"
Dynamic: license-file
